{
    "AutoApprovalTime": "2018-04-30T21:30:42Z",
    "AssignmentId": "3WEV0KO0ON5HY0FPFPPTHGCBTVFDSB",
    "WorkerId": "A2NOA2YRKVTIBQ",
    "answers": {
        "rule_type": "SINGLE_FEAT",
        "test_data_fn": "./js/test_data_body_color_orange_2.json",
        "time_in_minutes": null,
        "training_summary_stats": {
            "hits": 0,
            "misses": 0,
            "score": 0,
            "false_alarms": 0,
            "type": "training",
            "correct_rejections": 0
        },
        "testing_trials": [
            {
                "is_correct": true,
                "trial_num": 0,
                "turker_label": true,
                "time_in_seconds": 4.523,
                "true_label": true
            },
            {
                "is_correct": true,
                "trial_num": 1,
                "turker_label": true,
                "time_in_seconds": 4.445,
                "true_label": true
            },
            {
                "is_correct": true,
                "trial_num": 2,
                "turker_label": true,
                "time_in_seconds": 4.145,
                "true_label": true
            },
            {
                "is_correct": true,
                "trial_num": 3,
                "turker_label": true,
                "time_in_seconds": 1.967,
                "true_label": true
            },
            {
                "is_correct": true,
                "trial_num": 4,
                "turker_label": false,
                "time_in_seconds": 3.577,
                "true_label": false
            },
            {
                "is_correct": true,
                "trial_num": 5,
                "turker_label": false,
                "time_in_seconds": 2.394,
                "true_label": false
            },
            {
                "is_correct": true,
                "trial_num": 6,
                "turker_label": false,
                "time_in_seconds": 1.871,
                "true_label": false
            },
            {
                "is_correct": true,
                "trial_num": 7,
                "turker_label": true,
                "time_in_seconds": 1.827,
                "true_label": true
            },
            {
                "is_correct": true,
                "trial_num": 8,
                "turker_label": false,
                "time_in_seconds": 2.199,
                "true_label": false
            },
            {
                "is_correct": true,
                "trial_num": 9,
                "turker_label": true,
                "time_in_seconds": 2.543,
                "true_label": true
            },
            {
                "is_correct": true,
                "trial_num": 10,
                "turker_label": false,
                "time_in_seconds": 2.373,
                "true_label": false
            },
            {
                "is_correct": true,
                "trial_num": 11,
                "turker_label": false,
                "time_in_seconds": 1.951,
                "true_label": false
            },
            {
                "is_correct": true,
                "trial_num": 12,
                "turker_label": false,
                "time_in_seconds": 1.86,
                "true_label": false
            },
            {
                "is_correct": true,
                "trial_num": 13,
                "turker_label": false,
                "time_in_seconds": 1.867,
                "true_label": false
            },
            {
                "is_correct": true,
                "trial_num": 14,
                "turker_label": true,
                "time_in_seconds": 1.993,
                "true_label": true
            },
            {
                "is_correct": true,
                "trial_num": 15,
                "turker_label": false,
                "time_in_seconds": 3.683,
                "true_label": false
            },
            {
                "is_correct": true,
                "trial_num": 16,
                "turker_label": false,
                "time_in_seconds": 1.742,
                "true_label": false
            },
            {
                "is_correct": true,
                "trial_num": 17,
                "turker_label": false,
                "time_in_seconds": 1.819,
                "true_label": false
            },
            {
                "is_correct": true,
                "trial_num": 18,
                "turker_label": false,
                "time_in_seconds": 1.725,
                "true_label": false
            },
            {
                "is_correct": true,
                "trial_num": 19,
                "turker_label": false,
                "time_in_seconds": 2.505,
                "true_label": false
            },
            {
                "is_correct": true,
                "trial_num": 20,
                "turker_label": false,
                "time_in_seconds": 2.223,
                "true_label": false
            },
            {
                "is_correct": true,
                "trial_num": 21,
                "turker_label": true,
                "time_in_seconds": 2.141,
                "true_label": true
            },
            {
                "is_correct": true,
                "trial_num": 22,
                "turker_label": false,
                "time_in_seconds": 1.676,
                "true_label": false
            },
            {
                "is_correct": true,
                "trial_num": 23,
                "turker_label": false,
                "time_in_seconds": 1.858,
                "true_label": false
            },
            {
                "is_correct": true,
                "trial_num": 24,
                "turker_label": false,
                "time_in_seconds": 1.252,
                "true_label": false
            },
            {
                "is_correct": true,
                "trial_num": 25,
                "turker_label": true,
                "time_in_seconds": 1.767,
                "true_label": true
            },
            {
                "is_correct": true,
                "trial_num": 26,
                "turker_label": true,
                "time_in_seconds": 1.717,
                "true_label": true
            },
            {
                "is_correct": true,
                "trial_num": 27,
                "turker_label": false,
                "time_in_seconds": 2.486,
                "true_label": false
            },
            {
                "is_correct": true,
                "trial_num": 28,
                "turker_label": false,
                "time_in_seconds": 2.497,
                "true_label": false
            },
            {
                "is_correct": true,
                "trial_num": 29,
                "turker_label": true,
                "time_in_seconds": 2.711,
                "true_label": true
            },
            {
                "is_correct": true,
                "trial_num": 30,
                "turker_label": false,
                "time_in_seconds": 1.607,
                "true_label": false
            }
        ],
        "system": {
            "screenW": 1536,
            "screenH": 864,
            "OS": "Windows",
            "Browser": "Chrome"
        },
        "training_data_fn": "./js/training_data_body_color_orange_2.json",
        "role": "student",
        "training_trials": [],
        "subject_information": {
            "enjoyment": "2",
            "gender": "Female",
            "age": "27",
            "problems": "None at all",
            "nativeEnglish": "yes",
            "strategy": "Reading the instructions TWICE, then following my partners directions to a T. Fortunately, the instructions given by my partner were very clear. ",
            "assess": "yes",
            "humanPartner": "yes",
            "fairprice": "1.20",
            "comments": "Loved this experiment, would be very interested in doing more like it!",
            "likePartner": "loved",
            "education": "2"
        },
        "game_id": "7109-b1889f8c-acb5-4786-b2ca-8ea088c1bee1",
        "testing_summary_stats": {
            "hits": 11,
            "misses": 0,
            "score": 11,
            "false_alarms": 0,
            "type": "testing",
            "correct_rejections": 20
        },
        "rule_idx": 1
    },
    "AcceptTime": "2018-04-30T21:12:11Z",
    "HITId": "3VZYA8PITOBJ6UJQ1EJOLFMGUMY506",
    "Assignment": "",
    "AssignmentStatus": "Submitted",
    "SubmitTime": "2018-04-30T21:25:42Z"
}